[
  {
    "id": "streak-3",
    "name": "Warming Up",
    "description": "Maintain a 3-day learning streak",
    "tier": "bronze",
    "icon": "🔥",
    "criteria": { "type": "streak", "days": 3 }
  },
  {
    "id": "streak-7",
    "name": "On a Roll",
    "description": "Maintain a 7-day learning streak",
    "tier": "silver",
    "icon": "🔥",
    "criteria": { "type": "streak", "days": 7 }
  },
  {
    "id": "streak-14",
    "name": "Committed Learner",
    "description": "Maintain a 14-day learning streak",
    "tier": "gold",
    "icon": "🔥",
    "criteria": { "type": "streak", "days": 14 }
  },
  {
    "id": "streak-30",
    "name": "Unstoppable",
    "description": "Maintain a 30-day learning streak",
    "tier": "platinum",
    "icon": "💎",
    "criteria": { "type": "streak", "days": 30 }
  },
  {
    "id": "streak-100",
    "name": "Century Club",
    "description": "Maintain a 100-day learning streak",
    "tier": "platinum",
    "icon": "👑",
    "criteria": { "type": "streak", "days": 100 }
  },
  {
    "id": "exercise-first",
    "name": "First Steps",
    "description": "Complete your first exercise",
    "tier": "bronze",
    "icon": "✏️",
    "criteria": { "type": "exercises_completed", "count": 1 }
  },
  {
    "id": "exercise-50",
    "name": "Practitioner",
    "description": "Complete 50 exercises",
    "tier": "silver",
    "icon": "📝",
    "criteria": { "type": "exercises_completed", "count": 50 }
  },
  {
    "id": "exercise-100",
    "name": "Centurion",
    "description": "Complete 100 exercises",
    "tier": "gold",
    "icon": "💪",
    "criteria": { "type": "exercises_completed", "count": 100 }
  },
  {
    "id": "exercise-500",
    "name": "Exercise Machine",
    "description": "Complete 500 exercises",
    "tier": "platinum",
    "icon": "🏋️",
    "criteria": { "type": "exercises_completed", "count": 500 }
  },
  {
    "id": "mastery-first-domain",
    "name": "Domain Expert",
    "description": "Achieve mastery in your first domain",
    "tier": "silver",
    "icon": "⭐",
    "criteria": { "type": "domains_mastered", "count": 1 }
  },
  {
    "id": "mastery-track-complete",
    "name": "Track Champion",
    "description": "Master all domains in a single track",
    "tier": "gold",
    "icon": "🏆",
    "criteria": { "type": "track_mastered", "count": 1 }
  },
  {
    "id": "mastery-all-tracks",
    "name": "Grand Master",
    "description": "Master all domains across all 4 tracks",
    "tier": "platinum",
    "icon": "🎓",
    "criteria": { "type": "all_tracks_mastered" }
  },
  {
    "id": "mastery-five-stars",
    "name": "Perfectionist",
    "description": "Earn 5 stars in any domain",
    "tier": "gold",
    "icon": "🌟",
    "criteria": { "type": "five_star_domain", "count": 1 }
  },
  {
    "id": "speed-lesson",
    "name": "Speed Reader",
    "description": "Complete a lesson in under 5 minutes",
    "tier": "bronze",
    "icon": "⚡",
    "criteria": { "type": "lesson_speed", "maxSeconds": 300 }
  },
  {
    "id": "speed-perfect-assessment",
    "name": "Flawless",
    "description": "Score 100% on a module assessment",
    "tier": "gold",
    "icon": "💯",
    "criteria": { "type": "perfect_assessment" }
  },
  {
    "id": "social-case-study",
    "name": "Case Cracker",
    "description": "Complete your first case study",
    "tier": "bronze",
    "icon": "🔍",
    "criteria": { "type": "case_study_completed", "count": 1 }
  },
  {
    "id": "social-five-case-studies",
    "name": "Analyst",
    "description": "Complete 5 case studies",
    "tier": "silver",
    "icon": "📊",
    "criteria": { "type": "case_study_completed", "count": 5 }
  },
  {
    "id": "special-early-adopter",
    "name": "Early Adopter",
    "description": "Join Medinformics during the beta period",
    "tier": "platinum",
    "icon": "🚀",
    "criteria": { "type": "early_adopter" }
  },
  {
    "id": "special-first-certificate",
    "name": "Certified",
    "description": "Earn your first certificate",
    "tier": "gold",
    "icon": "📜",
    "criteria": { "type": "certificate_earned", "count": 1 }
  },
  {
    "id": "special-final-exam",
    "name": "Graduate",
    "description": "Pass a final exam",
    "tier": "platinum",
    "icon": "🎉",
    "criteria": { "type": "final_exam_passed" }
  }
]
